particlepy/__init__.py
particlepy/math.py
particlepy/particle.py
particlepy/shape.py
particlepy-1.1.0.dist-info/LICENSE
particlepy-1.1.0.dist-info/METADATA
particlepy-1.1.0.dist-info/WHEEL
particlepy-1.1.0.dist-info/top_level.txt
particlepy-1.1.0.dist-info/RECORD
