Metadata-Version: 2.1
Name: particlepy
Version: 1.1.0
Summary: A short library for easy to use particles in Pygame.
Home-page: https://github.com/grimmigerFuchs/ParticlePy
Author: grimmigerFuchs
Author-email: grimmigerFuchs@gmail.com
License: MIT
Project-URL: GitHub, https://github.com/grimmigerFuchs/ParticlePy
Project-URL: Bugtracker, https://github.com/grimmigerFuchs/ParticlePy/issues
Project-URL: Documentation, https://particlepy.readthedocs.io/
Keywords: game,simulation,game-development,pygame,particles,particle-physics,particle-system
Platform: UNKNOWN
Classifier: Intended Audience :: Developers
Classifier: Intended Audience :: Education
Classifier: License :: OSI Approved :: MIT License
Classifier: Natural Language :: English
Classifier: Programming Language :: Python
Classifier: Programming Language :: Python :: 3
Classifier: Programming Language :: Python :: 3.6
Classifier: Programming Language :: Python :: 3.7
Classifier: Programming Language :: Python :: 3.8
Classifier: Programming Language :: Python :: 3.9
Classifier: Programming Language :: Python :: Implementation :: PyPy
Classifier: Topic :: Games/Entertainment
Classifier: Topic :: Software Development :: Libraries :: Python Modules
Classifier: Topic :: Software Development :: Libraries :: pygame
Requires-Python: >=3.6.0
Requires-Dist: pygame
Requires-Dist: numpy
